{
    "example_source": [
        "x我还",
        "澄清",
        "了",
        "在该",
        "会议上",
        "提出的",
        "若干",
        "事项",
        "。"
    ],
    "example_target": [
        "<s>",
        "xi",
        "xwas",
        "xable",
        "xto",
        "xprovide",
        "xclarification",
        "xon",
        "xsome",
        "xof",
        "xthe",
        "xmatters",
        "xwhich",
        "xwere",
        "xraised",
        "xat",
        "xthat",
        "xmeeting",
        ".",
        "</s>"
    ],
    "hypotheses": [
        {
            "hypothesis": [
                "xi",
                "xalso",
                "xclarified",
                "xa",
                "xnumber",
                "xof",
                "xissues",
                "xraised",
                "xby",
                "xa",
                "xnumber",
                "xof",
                "xmatters",
                "."
            ],
            "score": -11.851861953735352
        },
        {
            "hypothesis": [
                "xi",
                "xalso",
                "xclarified",
                "xa",
                "xnumber",
                "xof",
                "xissues",
                "xraised",
                "xby",
                "xa",
                "xnumber",
                "xof",
                "xissues",
                "."
            ],
            "score": -11.867413520812988
        },
        {
            "hypothesis": [
                "xi",
                "xalso",
                "xclarified",
                "xa",
                "xnumber",
                "xof",
                "xmatters",
                "xraised",
                "xby",
                "xa",
                "xnumber",
                "xof",
                "xmatters",
                "."
            ],
            "score": -11.975662231445312
        },
        {
            "hypothesis": [
                "xi",
                "xalso",
                "xclarified",
                "xa",
                "xnumber",
                "xof",
                "xmatters",
                "xraised",
                "xby",
                "xa",
                "xnumber",
                "xof",
                "xissues",
                "."
            ],
            "score": -11.988957405090332
        },
        {
            "hypothesis": [
                "xi",
                "xalso",
                "xclarification",
                "xon",
                "xa",
                "xnumber",
                "xof",
                "xmatters",
                "xraised",
                "xby",
                "xa",
                "xnumber",
                "xof",
                "xmatters",
                "."
            ],
            "score": -12.6061429977417
        },
        {
            "hypothesis": [
                "xi",
                "xalso",
                "xclarification",
                "xon",
                "xa",
                "xnumber",
                "xof",
                "xmatters",
                "xraised",
                "xby",
                "xa",
                "xnumber",
                "xof",
                "xissues",
                "."
            ],
            "score": -12.676559448242188
        },
        {
            "hypothesis": [
                "xi",
                "xalso",
                "xclarified",
                "xa",
                "xnumber",
                "xof",
                "xissues",
                "xraised",
                "xby",
                "xa",
                "xnumber",
                "xof",
                "xmatters",
                "xraised",
                "xby",
                "xthe",
                "xmeeting",
                "."
            ],
            "score": -14.701762199401855
        },
        {
            "hypothesis": [
                "xi",
                "xalso",
                "xclarified",
                "xa",
                "xnumber",
                "xof",
                "xmatters",
                "xraised",
                "xby",
                "xa",
                "xnumber",
                "xof",
                "xmatters",
                "xraised",
                "xby",
                "xthe",
                "xmeeting",
                "."
            ],
            "score": -14.759079933166504
        },
        {
            "hypothesis": [
                "xi",
                "xalso",
                "xclarification",
                "xon",
                "xa",
                "xnumber",
                "xof",
                "xmatters",
                "xraised",
                "xby",
                "xa",
                "xnumber",
                "xof",
                "xmatters",
                "xraised",
                "xby",
                "xthe",
                "xmeeting",
                "."
            ],
            "score": -15.233649253845215
        },
        {
            "hypothesis": [
                "xi",
                "xalso",
                "xclarified",
                "xa",
                "xnumber",
                "xof",
                "xmatters",
                "xraised",
                "xby",
                "xa",
                "xnumber",
                "xof",
                "xmatters",
                "xraised",
                "xby",
                "xa",
                "xnumber",
                "xof",
                "xmatters",
                "."
            ],
            "score": -16.403797149658203
        }
    ],
    "diagnostic_info": "eyJ0IjogIjIwMjUtMTAtMTZUMTE6MDc6NDQuMTgyMjk5IiwgImgiOiAiVmllc3VraSIsICJ1IjogInFzemhlIn0="
}