{
    "example_source": [
        "x我还",
        "澄清",
        "了",
        "在该",
        "会议上",
        "提出的",
        "若干",
        "事项",
        "。"
    ],
    "example_target": [
        "<s>",
        "xi",
        "xwas",
        "xable",
        "xto",
        "xprovide",
        "xclarification",
        "xon",
        "xsome",
        "xof",
        "xthe",
        "xmatters",
        "xwhich",
        "xwere",
        "xraised",
        "xat",
        "xthat",
        "xmeeting",
        ".",
        "</s>"
    ],
    "hypotheses": [
        {
            "hypothesis": [
                "xi",
                "xwould",
                "xalso",
                "xlike",
                "xto",
                "xclarify",
                "xa",
                "xnumber",
                "xof",
                "xissues",
                "xthat",
                "xhave",
                "xtaken",
                "xplace",
                "xat",
                "xthe",
                "xmeeting",
                "."
            ],
            "score": -13.49241828918457
        },
        {
            "hypothesis": [
                "xi",
                "xwould",
                "xalso",
                "xlike",
                "xto",
                "xclarify",
                "xa",
                "xnumber",
                "xof",
                "xissues",
                "xthat",
                "xhave",
                "xtaken",
                "xplace",
                "xin",
                "xthe",
                "xmeeting",
                "."
            ],
            "score": -13.89799976348877
        },
        {
            "hypothesis": [
                "xi",
                "xwould",
                "xalso",
                "xlike",
                "xto",
                "xclarify",
                "xa",
                "xnumber",
                "xof",
                "xissues",
                "xthat",
                "xhave",
                "xbeen",
                "xraised",
                "xat",
                "xthe",
                "xmeeting",
                "."
            ],
            "score": -14.126029014587402
        },
        {
            "hypothesis": [
                "xi",
                "xwould",
                "xalso",
                "xlike",
                "xto",
                "xclarify",
                "xa",
                "xnumber",
                "xof",
                "xissues",
                "xthat",
                "xhave",
                "xtaken",
                "xplace",
                "xat",
                "xthe",
                "xsession",
                "."
            ],
            "score": -14.146573066711426
        },
        {
            "hypothesis": [
                "xi",
                "xwould",
                "xalso",
                "xlike",
                "xto",
                "xclarify",
                "xa",
                "xnumber",
                "xof",
                "xissues",
                "xthat",
                "xhave",
                "xtaken",
                "xplace",
                "xdur",
                "ing",
                "xthe",
                "xsession",
                "."
            ],
            "score": -14.627867698669434
        },
        {
            "hypothesis": [
                "xi",
                "xwould",
                "xalso",
                "xlike",
                "xto",
                "xclarify",
                "xa",
                "xnumber",
                "xof",
                "xissues",
                "xthat",
                "xhave",
                "xtaken",
                "xplace",
                "xat",
                "xthe",
                "xsession",
                "xof",
                "xthe",
                "xconference",
                "."
            ],
            "score": -14.986872673034668
        },
        {
            "hypothesis": [
                "xi",
                "xwould",
                "xalso",
                "xlike",
                "xto",
                "xclarify",
                "xa",
                "xnumber",
                "xof",
                "xissues",
                "xthat",
                "xhave",
                "xtaken",
                "xplace",
                "xat",
                "xthe",
                "xsession",
                "xof",
                "xthe",
                "xmeeting",
                "."
            ],
            "score": -15.29013442993164
        },
        {
            "hypothesis": [
                "xi",
                "xwould",
                "xalso",
                "xlike",
                "xto",
                "xclarify",
                "xa",
                "xnumber",
                "xof",
                "xissues",
                "xthat",
                "xhave",
                "xtaken",
                "xplace",
                "xat",
                "xthe",
                "xmeeting",
                "xof",
                "xthe",
                "xconference",
                "."
            ],
            "score": -15.506669044494629
        },
        {
            "hypothesis": [
                "xi",
                "xwould",
                "xalso",
                "xlike",
                "xto",
                "xclarify",
                "xa",
                "xnumber",
                "xof",
                "xissues",
                "xthat",
                "xhave",
                "xtaken",
                "xplace",
                "xat",
                "xthe",
                "xmeeting",
                "xof",
                "xthe",
                "xmeeting",
                "."
            ],
            "score": -15.585814476013184
        },
        {
            "hypothesis": [
                "xi",
                "xwould",
                "xalso",
                "xlike",
                "xto",
                "xclarify",
                "xa",
                "xnumber",
                "xof",
                "xissues",
                "xthat",
                "xhave",
                "xtaken",
                "xplace",
                "xdur",
                "ing",
                "xthe",
                "xsession",
                "xof",
                "xthe",
                "xmeeting",
                "."
            ],
            "score": -16.46499252319336
        }
    ],
    "diagnostic_info": "eyJ0IjogIjIwMjUtMTAtMTZUMTE6MjE6MTEuMDIzMzcyIiwgImgiOiAiVmllc3VraSIsICJ1IjogInFzemhlIn0="
}