{
    "example_source": [
        "x我还",
        "澄清",
        "了",
        "在该",
        "会议上",
        "提出的",
        "若干",
        "事项",
        "。"
    ],
    "example_target": [
        "<s>",
        "xi",
        "xwas",
        "xable",
        "xto",
        "xprovide",
        "xclarification",
        "xon",
        "xsome",
        "xof",
        "xthe",
        "xmatters",
        "xwhich",
        "xwere",
        "xraised",
        "xat",
        "xthat",
        "xmeeting",
        ".",
        "</s>"
    ],
    "hypotheses": [
        {
            "hypothesis": [
                "xi",
                "xalso",
                "xclarified",
                "xa",
                "xnumber",
                "xof",
                "xmatters",
                "xraised",
                "xat",
                "xthat",
                "xmeeting",
                "."
            ],
            "score": -5.370477676391602
        },
        {
            "hypothesis": [
                "xi",
                "xalso",
                "xclarified",
                "xa",
                "xnumber",
                "xof",
                "xmatters",
                "xraised",
                "xat",
                "xthis",
                "xmeeting",
                "."
            ],
            "score": -6.2897562980651855
        },
        {
            "hypothesis": [
                "xwe",
                "xalso",
                "xclarified",
                "xa",
                "xnumber",
                "xof",
                "xmatters",
                "xraised",
                "xat",
                "xthat",
                "xmeeting",
                "."
            ],
            "score": -6.467841625213623
        },
        {
            "hypothesis": [
                "xi",
                "xalso",
                "xclarified",
                "xa",
                "xnumber",
                "xof",
                "xmatters",
                "xraised",
                "xat",
                "xthat",
                "xthat",
                "xmeeting",
                "."
            ],
            "score": -6.729400634765625
        },
        {
            "hypothesis": [
                "xi",
                "xalso",
                "xclarified",
                "xa",
                "xnumber",
                "xof",
                "xissues",
                "xthat",
                "xhave",
                "xbeen",
                "xraised",
                "xat",
                "xthat",
                "xmeeting",
                "."
            ],
            "score": -7.2194600105285645
        },
        {
            "hypothesis": [
                "xi",
                "xalso",
                "xclarified",
                "xa",
                "xnumber",
                "xof",
                "xmatters",
                "xthat",
                "xhave",
                "xbeen",
                "xraised",
                "xat",
                "xthat",
                "xmeeting",
                "."
            ],
            "score": -7.3814287185668945
        },
        {
            "hypothesis": [
                "xi",
                "xalso",
                "xclarified",
                "xa",
                "xnumber",
                "xof",
                "xmatters",
                "xput",
                "xin",
                "xplace",
                "xat",
                "xthat",
                "xmeeting",
                "."
            ],
            "score": -7.518433570861816
        },
        {
            "hypothesis": [
                "xi",
                "xalso",
                "xclarified",
                "xa",
                "xnumber",
                "xof",
                "xissues",
                "xthat",
                "xhave",
                "xbeen",
                "xput",
                "xin",
                "xplace",
                "xat",
                "xthat",
                "xmeeting",
                "."
            ],
            "score": -8.465740203857422
        },
        {
            "hypothesis": [
                "xi",
                "xalso",
                "xclarified",
                "xa",
                "xnumber",
                "xof",
                "xissues",
                "xthat",
                "xhave",
                "xbeen",
                "xraised",
                "xat",
                "xthat",
                "xthat",
                "xmeeting",
                "."
            ],
            "score": -8.920426368713379
        },
        {
            "hypothesis": [
                "xi",
                "xalso",
                "xclarified",
                "xa",
                "xnumber",
                "xof",
                "xmatters",
                "xthat",
                "xhave",
                "xbeen",
                "xraised",
                "xat",
                "xthat",
                "xthat",
                "xmeeting",
                "."
            ],
            "score": -9.025642395019531
        }
    ],
    "diagnostic_info": "eyJ0IjogIjIwMjUtMTAtMTZUMTI6MjU6MDguNzU0NTA3IiwgImgiOiAiVmllc3VraSIsICJ1IjogInFzemhlIn0="
}