{
    "example_source": [
        "x我还",
        "澄清",
        "了",
        "在该",
        "会议上",
        "提出的",
        "若干",
        "事项",
        "。"
    ],
    "example_target": [
        "<s>",
        "xi",
        "xwas",
        "xable",
        "xto",
        "xprovide",
        "xclarification",
        "xon",
        "xsome",
        "xof",
        "xthe",
        "xmatters",
        "xwhich",
        "xwere",
        "xraised",
        "xat",
        "xthat",
        "xmeeting",
        ".",
        "</s>"
    ],
    "hypotheses": [
        {
            "hypothesis": [
                "xi",
                "xalso",
                "xclarified",
                "xa",
                "xnumber",
                "xof",
                "xmatters",
                "xraised",
                "xat",
                "xthat",
                "xmeeting",
                "."
            ],
            "score": -5.728186130523682
        },
        {
            "hypothesis": [
                "xi",
                "xhave",
                "xalso",
                "xclarified",
                "xa",
                "xnumber",
                "xof",
                "xmatters",
                "xraised",
                "xat",
                "xthat",
                "xmeeting",
                "."
            ],
            "score": -6.0824737548828125
        },
        {
            "hypothesis": [
                "xi",
                "xalso",
                "xclarified",
                "xa",
                "xnumber",
                "xof",
                "xmatters",
                "xraised",
                "xat",
                "xthis",
                "xmeeting",
                "."
            ],
            "score": -6.461940288543701
        },
        {
            "hypothesis": [
                "xwe",
                "xalso",
                "xclarified",
                "xa",
                "xnumber",
                "xof",
                "xmatters",
                "xraised",
                "xat",
                "xthat",
                "xmeeting",
                "."
            ],
            "score": -6.5953826904296875
        },
        {
            "hypothesis": [
                "xi",
                "xhave",
                "xclarified",
                "xa",
                "xnumber",
                "xof",
                "xmatters",
                "xraised",
                "xat",
                "xthat",
                "xmeeting",
                "."
            ],
            "score": -6.754101276397705
        },
        {
            "hypothesis": [
                "xi",
                "xhave",
                "xalso",
                "xclarified",
                "xa",
                "xnumber",
                "xof",
                "xmatters",
                "xraised",
                "xat",
                "xthis",
                "xmeeting",
                "."
            ],
            "score": -6.789938449859619
        },
        {
            "hypothesis": [
                "xi",
                "xhave",
                "xalso",
                "xclarified",
                "xa",
                "xnumber",
                "xof",
                "xmatters",
                "xraised",
                "xby",
                "xthe",
                "xconference",
                "."
            ],
            "score": -7.39145040512085
        },
        {
            "hypothesis": [
                "xi",
                "xhave",
                "xalso",
                "xclarified",
                "xa",
                "xnumber",
                "xof",
                "xmatters",
                "xthat",
                "xhave",
                "xbeen",
                "xraised",
                "xat",
                "xthat",
                "xmeeting",
                "."
            ],
            "score": -8.24148178100586
        },
        {
            "hypothesis": [
                "xi",
                "xhave",
                "xclarified",
                "xa",
                "xnumber",
                "xof",
                "xmatters",
                "xraised",
                "xat",
                "xthat",
                "xmeeting",
                ",",
                "xclarified",
                "."
            ],
            "score": -8.37831974029541
        },
        {
            "hypothesis": [
                "xi",
                "xhave",
                "xalso",
                "xclarified",
                "xa",
                "xnumber",
                "xof",
                "xmatters",
                "xthat",
                "xhave",
                "xbeen",
                "xput",
                "xin",
                "xplace",
                "xat",
                "xthat",
                "xmeeting",
                "."
            ],
            "score": -9.020877838134766
        }
    ],
    "diagnostic_info": "eyJ0IjogIjIwMjUtMTAtMTZUMTI6MzE6NDAuMDMyOTk0IiwgImgiOiAiVmllc3VraSIsICJ1IjogInFzemhlIn0="
}